LICENSE
MANIFEST.in
README.md
dev-requirements.txt
pyproject.toml
setup.cfg
setup.py
versioneer.py
fideslog.egg-info/PKG-INFO
fideslog.egg-info/SOURCES.txt
fideslog.egg-info/dependency_links.txt
fideslog.egg-info/requires.txt
fideslog.egg-info/top_level.txt
fideslog/api/requirements.txt
fideslog/sdk/python/README.md
fideslog/sdk/python/__init__.py
fideslog/sdk/python/_version.py
fideslog/sdk/python/client.py
fideslog/sdk/python/event.py
fideslog/sdk/python/exceptions.py
fideslog/sdk/python/registration.py
fideslog/sdk/python/requirements.txt
fideslog/sdk/python/utils.py