Metadata-Version: 2.1
Name: fideslog
Version: 1.2.15
Summary: The fideslog analytics collection mechanism
Home-page: https://github.com/ethyca/fideslog
Author: Ethyca, Inc.
Author-email: fidesteam@ethyca.com
License: Apache License 2.0
Classifier: License :: OSI Approved :: Apache Software License
Classifier: Programming Language :: Python :: 3 :: Only
Classifier: Programming Language :: Python :: 3.8
Classifier: Programming Language :: Python :: 3.9
Classifier: Topic :: Software Development :: Libraries
Requires-Python: >=3.8, <4
License-File: LICENSE
